freecad_mcp/__init__.py
freecad_mcp/py.typed
freecad_mcp/server.py
mseep_freecad_mcp-0.1.16.dist-info/licenses/LICENSE
mseep_freecad_mcp-0.1.16.dist-info/METADATA
mseep_freecad_mcp-0.1.16.dist-info/WHEEL
mseep_freecad_mcp-0.1.16.dist-info/entry_points.txt
mseep_freecad_mcp-0.1.16.dist-info/top_level.txt
mseep_freecad_mcp-0.1.16.dist-info/RECORD
